labx/__init__.py
labx/client.py
labx/tests/__init__.py
labx/tests/test_client.py
labx_py-2025.9.2.dist-info/licenses/LICENSE
labx_py-2025.9.2.dist-info/METADATA
labx_py-2025.9.2.dist-info/WHEEL
labx_py-2025.9.2.dist-info/top_level.txt
labx_py-2025.9.2.dist-info/RECORD
