Metadata-Version: 2.4
Name: labx-py
Version: 2025.9.2
Summary: Labx Python Client
Author-email: "Zi-Jian Yi (伊子健)" <arrowzeke@gmail.com>
License: GPL
Project-URL: Repository, https://github.com/i-z-j/labx-py
Keywords: labx,labserver
Classifier: Programming Language :: Python :: 3
Classifier: License :: OSI Approved :: GNU General Public License v3 (GPLv3)
Requires-Python: >=3.10
License-File: LICENSE
Requires-Dist: httpx>=0.28.1
Requires-Dist: pydantic>=2.11.7
Dynamic: license-file
